{
  "slug": "anthropoid-spider",
  "name": "ANTHROPOID SPIDER",
  "uuid": null,
  "description": "Publicly known as 'EmpireMonkey', ANTHROPOID SPIDER conducted phishing campaigns in February and March 2019, spoofing French, Norwegian and Belizean financial regulators and institutions. These campaigns used macro-enabled Microsoft documents to deliver the PowerShell Empire post-exploitation framework. ANTHROPOID SPIDER likely enabled a breach that allegedly involved fraudulent transfers over the SWIFT network.",
  "aliases": [
    "Empire Monkey",
    "CobaltGoblin"
  ],
  "refs": [
    "https://go.crowdstrike.com/rs/281-OBQ-266/images/Report2020CrowdStrikeGlobalThreatReport.pdf",
    "https://www.kaspersky.com/about/press-releases/2019_fin7-hacking-group-targets-more-than-130-companies-after-leaders-arrest",
    "https://fortiguard.com/encyclopedia/botnet/7630456"
  ],
  "country": null,
  "countries": null,
  "sectors": null,
  "first_seen": null,
  "last_seen": null,
  "related": [],
  "rawMeta": {
    "sources": [
      "MISP:threat-actor"
    ],
    "description_sources": [
      "MISP:threat-actor"
    ],
    "external_ids": null,
    "entity_type": "intrusion-set",
    "ttp_mappings": []
  },
  "order": 0
}
