{
  "slug": "cheers",
  "name": "cheers",
  "uuid": null,
  "description": "",
  "aliases": [],
  "refs": [
    "http://rwiajgajdr4kzlnrj5zwebbukpcbrjhupjmk6gufxv6tg7myx34iocad.onion/",
    "http://crkfkmrh4qzbddfrl2axnkvjp5tgwx73d7lq4oycsfxc7pfgbfhtfiid.onion/"
  ],
  "country": null,
  "countries": null,
  "sectors": null,
  "first_seen": null,
  "last_seen": null,
  "related": [],
  "rawMeta": {
    "sources": [
      "RWLive"
    ],
    "description_sources": null,
    "external_ids": null,
    "entity_type": "intrusion-set",
    "ttp_mappings": []
  },
  "order": 0
}
