{
  "slug": "cosmic-lynx",
  "name": "Cosmic Lynx",
  "uuid": null,
  "description": "Cosmic Lynx is a Russia-based BEC cybercriminal organization that has significantly impacted the email threat landscape with sophisticated, high-dollar phishing attacks.",
  "aliases": [],
  "refs": [
    "https://www.agari.com/cyber-intelligence-research/whitepapers/acid-agari-cosmic-lynx.pdf"
  ],
  "country": null,
  "countries": null,
  "sectors": null,
  "first_seen": null,
  "last_seen": null,
  "related": [],
  "rawMeta": {
    "sources": [
      "MISP:threat-actor"
    ],
    "description_sources": [
      "MISP:threat-actor"
    ],
    "external_ids": null,
    "entity_type": "intrusion-set",
    "ttp_mappings": []
  },
  "order": 0
}
