{
  "slug": "fishmedley",
  "name": "FishMedley",
  "uuid": null,
  "description": "Verticals targeted during Operation FishMedley include governments, NGOs, and think tanks, across Asia, Europe, and the United States. ; Operators used implants – such as ShadowPad, SodaMaster, and Spyder – that are common or exclusive to China-aligned threat actors. ; We assess with high confidence that Operation FishMedley was conducted by the FishMonger APT group.",
  "aliases": [],
  "refs": [
    "https://www.welivesecurity.com/en/eset-research/operation-fishmedley/"
  ],
  "country": null,
  "countries": null,
  "sectors": null,
  "related": [],
  "rawMeta": {
    "sources": [
      "MISP:threat-actor"
    ],
    "description_sources": [
      "MISP:threat-actor"
    ],
    "external_ids": null,
    "entity_type": "intrusion-set",
    "ttp_mappings": []
  },
  "order": 0
}
