{
  "slug": "indohaxsec-team",
  "name": "INDOHAXSEC TEAM",
  "uuid": null,
  "description": "INDOHAXSEC TEAM is an Indonesian group that claims to have developed a web-based version of WannaCry, asserting the ability to encrypt websites and demand Bitcoin as ransom. However, their technical capabilities remain uncertain, as creating ransomware of this scale requires significant expertise. The group's claims may be exaggerated for attention, and verified evidence is needed to assess their true capabilities.",
  "aliases": [],
  "refs": [
    "https://socradar.io/dark-peep-17-dark-web-hacker-forums-ransomware/"
  ],
  "country": "ID",
  "countries": [
    "ID"
  ],
  "sectors": null,
  "related": [],
  "rawMeta": {
    "sources": [
      "MISP:threat-actor"
    ],
    "description_sources": [
      "MISP:threat-actor"
    ],
    "external_ids": null,
    "entity_type": "intrusion-set",
    "ttp_mappings": []
  },
  "order": 0
}
