{
  "slug": "lulzsec-black",
  "name": "LulzSec Black",
  "uuid": "a86b67d2-fc94-4c1b-91e1-949c969176ed",
  "description": "LulzSec Black is a hacktivist group that has claimed responsibility for coordinated DDoS attacks against Cyprus' government and critical infrastructure in response to the country's support for Israel. They have also announced cyberattacks targeting the UAE, including breaches of a government website and Alfa Electronics, asserting these actions are in support of Palestine. The group has indicated intentions for further attacks and has not provided independently verifiable evidence of their claims. Their operations reflect a focus on disrupting services and compromising data as part of their political agenda.",
  "aliases": [],
  "refs": [
    "https://dailydarkweb.net/lulzsec-black-claims-cyberattacks-on-emirati-government-and-other-sector-targets/"
  ],
  "countries": [],
  "sectors": [],
  "related": [],
  "rawMeta": {
    "refs": [
      "https://dailydarkweb.net/lulzsec-black-claims-cyberattacks-on-emirati-government-and-other-sector-targets/"
    ]
  },
  "order": 755
}
