{
  "slug": "raspberry-typhoon",
  "name": "Raspberry Typhoon",
  "uuid": null,
  "description": "Microsoft has tracked Raspberry Typhoon (RADIUM) as the primary threat group targeting nations that ring the South China Sea. Raspberry Typhoon consistently targets government ministries, military entities, and corporate entities connected to critical infrastructure, particularly telecoms. Since January 2023, Raspberry Typhoon has been particularly persistent. When targeting government ministries or infrastructure, Raspberry Typhoon typically conducts intelligence collection and malware execution. In many countries, targets vary from defense and intelligence-related ministries to economic and trade-related ministries",
  "aliases": [
    "RADIUM"
  ],
  "refs": [
    "https://query.prod.cms.rt.microsoft.com/cms/api/am/binary/RW1aFyW"
  ],
  "country": "CN",
  "countries": [
    "CN"
  ],
  "sectors": null,
  "first_seen": null,
  "last_seen": null,
  "related": [],
  "rawMeta": {
    "sources": [
      "MISP:threat-actor"
    ],
    "description_sources": [
      "MISP:threat-actor"
    ],
    "external_ids": null,
    "entity_type": "intrusion-set",
    "ttp_mappings": []
  },
  "order": 0
}
