{
  "slug": "ta800",
  "name": "TA800",
  "uuid": null,
  "description": "This attacker is an affiliate distributor of the The Trick, also known as Trickbot, and BazaLoader. (For more on how affiliates work, see the description of TA573).\nTA800 has targeted a wide range of industries in North America, infecting victims with banking Trojans and malware loaders (malware designed to download other malware onto a compromised device). Malicious emails have often included recipients’ names, titles and employers along with phishing pages designed to look like the targeted company. Lures have included hard-to-resist subjects such as related to payment, meetings, termination, bonuses and complaints in the subject line or body of the email.",
  "aliases": [],
  "refs": [
    "https://www.proofpoint.com/us/blog/threat-insight/q4-2020-threat-report-quarterly-analysis-cybersecurity-trends-tactics-and-themes"
  ],
  "country": null,
  "countries": null,
  "sectors": null,
  "first_seen": null,
  "last_seen": null,
  "related": [],
  "rawMeta": {
    "sources": [
      "MISP:threat-actor"
    ],
    "description_sources": [
      "MISP:threat-actor"
    ],
    "external_ids": null,
    "entity_type": "intrusion-set",
    "ttp_mappings": []
  },
  "order": 0
}
